KnkPoolExecutor/__init__.py
KnkPoolExecutor/utils.py
KnKPoolExecutor-2.0.1.dist-info/LICENSE
KnKPoolExecutor-2.0.1.dist-info/METADATA
KnKPoolExecutor-2.0.1.dist-info/WHEEL
KnKPoolExecutor-2.0.1.dist-info/top_level.txt
KnKPoolExecutor-2.0.1.dist-info/RECORD
