Metadata-Version: 2.1
Name: KnKPoolExecutor
Version: 2.0.1
Summary: Extension of concurrent.futures for Cloud-Function-as-a-Service compatibility
Home-page: https://github.com/pahntanapat/knk-pool-executor
Author: Tanapat Kahabodeekanokkul, Natthaphong Ratchakhom
Author-email: pahntanapat@gmail.com
License: : OSI Approved :: MIT License
Project-URL: Bug Tracker, https://github.com/pahntanapat/knk-pool-executor/issues
Requires-Python: >=3.6
License-File: LICENSE
